Workbook
Name BudgetCategory: [1]!BudgetCategoryLookup[Budget Category Lookup]

Sheet All transactions
A1: Date | B1: Payee | C1: Amount | D1: Category | E1: Bas-Lux | F1: source
A2: 45861 | B2: Ext Credit Card Debit LITTLE UMBRELLA VANCOUVER BC | C2: 5.3 | D2: Dining | E2: Luxury | F2: ftcu
A3: 45860 | B3: Ext Credit Card Debit EXPEDIA HOTELCOM731800 UK.HOTELS.COMGB | C3: 156.07 | D3: Travel | E3: Luxury | F3: ftcu
A4: 45982 | B4: Ext Credit Card Debit BANK OF AMERICA SEATTLE DC | C4: -35 | D4: Cash | E4: Basic | F4: ftcu
A5: 45980 | B5: Ext Credit Card Credit PAYMENT - THANK YOU BEAVERTON OR | C5: -3.03 | D5: Transfer | E5: Basic | F5: ftcu
A6: 45929 | B6: Ext Credit Card Debit CASH ADVANCE BEAVERTON OR | C6: -104.55 | D6: Cash | E6: Basic | F6: ftcu
A7: 45923 | B7: Ext Credit Card Credit PAYMENT - THANK YOU BEAVERTON OR | C7: -303.86 | D7: Transfer | E7: Basic | F7: ftcu
A8: 45909 | B8: Ext Credit Card Credit PAYMENT - THANK YOU BEAVERTON OR | C8: -253 | D8: Transfer | E8: Basic | F8: ftcu
A9: 45909 | B9: Ext Credit Card Debit CASH ADVANCE BEAVERTON OR | C9: -316.57 | D9: Cash | E9: Basic | F9: ftcu
A10: 45898 | B10: Ext Credit Card Debit CASH ADVANCE BEAVERTON OR | C10: -203 | D10: Cash | E10: Basic | F10: ftcu
A11: 45889 | B11: Ext Credit Card Debit BANK OF AMERICA SEATTLE DC | C11: -8 | D11: Cash | E11: Basic | F11: ftcu
A12: 45878 | B12: Ext Credit Card Credit PAYMENT - THANK YOU BEAVERTON OR | C12: -32.31 | D12: Transfer | E12: Basic | F12: ftcu
A13: 45877 | B13: Ext Credit Card Credit PAYMENT - THANK YOU BEAVERTON OR | C13: -36.01 | D13: Transfer | E13: Basic | F13: ftcu
... A71: 45675 | B71: Ext Credit Card Debit Interest Charge on Cash A | C71: 148.68 | D71: Bank Fees | E71: Luxury | F71: ftcu
A72: 45835 | B72: Ext Credit Card Debit ZG * RENTAPPLICATION 206-516-2265 WA | C72: 35 | D72: 0 | E72: 0 | F72: ftcu
A73: 45828 | B73: Ext Credit Card Debit WAFISH&WILDLIC-SVC*FEE OLYMPIA WA | C73: 3.03 | D73: Travel | E73: Luxury | F73: ftcu
A74: 45828 | B74: Ext Credit Card Debit WA FISH & WILD LICENSE OLYMPIA WA | C74: 104.55 | D74: Travel | E74: Luxury | F74: ftcu
A75: 45801 | B75: Ext Credit Card Debit CL *TRIPCHARGES GLEN ALLEN VA | C75: 303.86 | D75: Travel | E75: Luxury | F75: ftcu
A76: 45789 | B76: Ext Credit Card Debit ACTBLUE* EILEEN.LAUBAC BOSTON MA | C76: 253 | D76: Charitable Contributions | E76: Luxury | F76: ftcu
A77: 45775 | B77: Ext Credit Card Debit CSAIRP90 WDP90725042679 PARIS FR | C77: 316.57 | D77: Travel | E77: Luxury | F77: ftcu
A78: 45709 | B78: Ext Credit Card Debit P462086 SEATTLE DC | C78: 203 | D78: 0 | E78: 0 | F78: ftcu
A79: 45868 | B79: Ext Credit Card Debit VM PARKING GARAGE SEATTLE WA | C79: 8 | D79: Auto | E79: Basic | F79: ftcu
A80: 45861 | B80: Ext Credit Card Debit HONK PARKING 866-675-7337 ON | C80: 32.31 | D80: Auto | E80: Basic | F80: ftcu
A81: 45857 | B81: Ext Credit Card Debit Interest Charge on Purcha | C81: 36.01 | D81: Bank Fees | E81: Luxury | F81: ftcu
A82: 45826 | B82: Ext Credit Card Debit Interest Charge on Purcha | C82: 32.91 | D82: Bank Fees | E82: Luxury | F82: ftcu
A83: 45796 | B83: Ext Credit Card Debit Interest Charge on Purcha | C83: 27.1 | D83: Bank Fees | E83: Luxury | F83: ftcu
A84: 45765 | B84: Ext Credit Card Debit Interest Charge on Purcha | C84: 27.1 | D84: Bank Fees | E84: Luxury | F84: ftcu
A85: 45735 | B85: Ext Credit Card Debit Interest Charge on Purcha | C85: 28.35 | D85: Bank Fees | E85: Luxury | F85: ftcu
A86: 45703 | B86: Ext Credit Card Debit Interest Charge on Purcha | C86: 37.87 | D86: Bank Fees | E86: Luxury | F86: ftcu
A87: 45675 | B87: Ext Credit Card Debit Interest Charge on Purcha | C87: 37.87 | D87: Bank Fees | E87: Luxury | F87: ftcu
A88: 45869 | B88: Ext Credit Card Debit EZELLS FAMOUS CHICKEN SEATTLE WA | C88: 34.97 | D88: Dining | E88: Luxury | F88: ftcu
A89: 45867 | B89: Ext Credit Card Debit CLEVER COW CREAMERY EASTSOUND WA | C89: 5.7 | D89: Dining | E89: Luxury | F89: ftcu
A90: 45866 | B90: Ext Credit Card Debit SQ *TAQUERIA AND PUPUS EASTSOUND WA | C90: 6.38 | D90: Dining | E90: Luxury | F90: ftcu
... A110: 45943 | B110: Ext Credit Card Credit 4297453 AUTOPAYLANG*!01 | C110: -11.53 | D110: Transfer | E110: Basic | F110: ftcu
A111: 45941 | B111: Lnvm | C111: 110.34 | E111: 0 | F111: usaa-cc
A112: 45981 | B112: Seattle University | C112: 19.5 | D112: Auto | E112: Basic | F112: usaa-cc
A113: 45954 | B113: Seattle University | C113: 10 | D113: Auto | E113: Basic | F113: usaa-cc
A114: 45946 | B114: Seattle University | C114: 30.91 | D114: Auto | E114: Basic | F114: usaa-cc
A115: 45944 | B115: Seattle University | C115: 15.59 | D115: Auto | E115: Basic | F115: usaa-cc
A116: 45963 | B116: Best Buy | C116: 308.97 | D116: Auto | E116: Basic | F116: usaa-cc
A117: 45949 | B117: Evergreen Guardian | C117: 35 | D117: Home & Garden | E117: Luxury | F117: usaa-cc
A118: 45942 | B118: Ian Windham | C118: 30.83 | D118: Travel | E118: Luxury | F118: usaa-cc
A119: 45954 | B119: Max | C119: 11.01 | D119: Subscriptions / Digital | E119: Luxury | F119: usaa-cc
A120: 45965 | B120: Tesla | C120: 11.02 | D120: Auto | E120: Basic | F120: usaa-cc
A121: 45934 | B121: Tesla | C121: 11.02 | D121: Auto | E121: Basic | F121: usaa-cc
A122: 45965 | B122: Seattle Municipal Court | C122: 78.6 | D122: Auto | E122: Luxury | F122: usaa-cc
A123: 45926 | B123: WSDOT-GOODTOGO ONLINE RENTON WA | C123: 100 | D123: Auto | E123: Basic | F123: usaa-cc
... A1901: 45878 | B1901: Crazy Sports Ltd. Adelboden CH | C1901: 37.27 | D1901: Enrichment | E1901: Basic | F1901: usaa-cc
A1902: 45853 | B1902: SRSMRKTPLACE.COM 9311 847-286-2500 IL | C1902: 38.68 | D1902: 0 | E1902: 0 | F1902: usaa-cc
A1903: 45896 | B1903: FRANK'S GENERAL STORE CHERRYVILLE CD | C1903: 39.35 | D1903: Groceries | E1903: Basic | F1903: usaa-cc
A1904: 45867 | B1904: SPO*MIRAKUTEISUSHI&RAMEN PORTLAND OR | C1904: 39.6 | D1904: Dining | E1904: Luxury | F1904: usaa-cc
A1905: 45859 | B1905: TSUTAYABUTSUKUSUTOAAPITSUTOKYO JP | C1905: 40.5 | D1905: Travel | E1905: Luxury | F1905: usaa-cc
A1906: 45897 | B1906: AAA WA MEMBERSHIP 00 800-562-2582 WA | C1906: 41.25 | D1906: Membership | E1906: Basic | F1906: usaa-cc
A1907: 45889 | B1907: JEBENA CAFE & MARKET LLC SEATTLE WA | C1907: 42.73 | D1907: Dining | E1907: Luxury | F1907: usaa-cc
A1908: 45878 | B1908: Oester Sport AG Adelboden CH | C1908: 43.48 | D1908: Enrichment | E1908: Basic | F1908: usaa-cc
A1909: 45856 | B1909: PAYPAL *MADRASCARTL 402-935-7733 CA | C1909: 43.53 | D1909: Groceries | E1909: Basic | F1909: usaa-cc
A1910: 45864 | B1910: SQ *PACHA COLLECTIVE Seattle WA | C1910: 44.42 | D1910: Clothing | E1910: Luxury | F1910: usaa-cc
A1911: 45896 | B1911: eBay O*17-13491-31996 Toronto CD | C1911: 44.78 | D1911: Clothing | E1911: Luxury | F1911: usaa-cc
A1912: 45986 | B1912: Tweed and Popp Hardware | C1912: 46.32 | D1912: Home & Garden | E1912: Basic | F1912: usaa-cc
A1913: 45863 | B1913: PAYPAL *PANTHER RV PANTHE402-935-7733 WA | C1913: 46.37 | D1913: Van | E1913: Luxury | F1913: usaa-cc
A1914: 45859 | B1914: AUTOBACS (POS) OSAKA JP | C1914: 46.55 | D1914: Travel | E1914: Luxury | F1914: usaa-cc
... A1930: 45914 | B1930: CIRCLE K # 09654 KIRKLAND WA | C1930: 54.9 | D1930: Auto | E1930: Basic | F1930: usaa-cc
A1931: 45878 | B1931: PAMPER HAUS 415-754-0166 CA | C1931: 55 | D1931: 0 | E1931: 0 | F1931: usaa-cc
A1932: 45903 | B1932: Vans Seattle Seattle WA | C1932: 55.26 | D1932: Clothing | E1932: Basic | F1932: usaa-cc
A1933: 45911 | B1933: TOTAL WINE AND MORE BELLEVUE WA | C1933: 56.18 | D1933: Groceries | E1933: Luxury | F1933: usaa-cc
A1934: 45866 | B1934: CASH ADVANCE FEE | C1934: 15 | D1934: Bank Fees | E1934: Luxury | F1934: usaa-cc
A1935: 45920 | B1935: PY *RANCHO SEDONA RV PARKSEDONA AZ | C1935: 57.39 | D1935: Travel | E1935: Luxury | F1935: usaa-cc
A1936: 45902 | B1936: TST*BA BAR - UNIVERSITY SEATTLE WA | C1936: 59.17 | D1936: Dining | E1936: Luxury | F1936: usaa-cc
A1937: 45987 | B1937: Buckaroo Annef | C1937: 59.17 | D1937: 0 | E1937: 0 | F1937: usaa-cc
A1938: 45868 | B1938: YAMAKARANA NARA JP | C1938: 59.41 | D1938: Travel | E1938: Luxury | F1938: usaa-cc
A1939: 45870 | B1939: 76 - ROOSEVELT 76 SEATTLE WA | C1939: 60 | D1939: Auto | E1939: Basic | F1939: usaa-cc
A1940: 45862 | B1940: ITOYA HONTEN TOKYO JP | C1940: 60.24 | D1940: Travel | E1940: Luxury | F1940: usaa-cc
A1941: 45910 | B1941: MARLAI FINE THAI CUISINE SEATTLE WA | C1941: 60.6 | D1941: Dining | E1941: Luxury | F1941: usaa-cc
A1942: 45891 | B1942: Etsy.com - Chicamaze 844-6593879 NY | C1942: 60.69 | D1942: Clothing | E1942: Luxury | F1942: usaa-cc
A1943: 45882 | B1943: ARCO#00818RED SEA SERVIC SEATTLE WA | C1943: 64.96 | D1943: Auto | E1943: Basic | F1943: usaa-cc
A1944: 45911 | B1944: UWAJIMAYA BELLEVUE BELLEVUE WA | C1944: 65.01 | D1944: Groceries | E1944: Basic | F1944: usaa-cc
A1945: 45931 | B1945: TST*BA BAR - UNIVERSITY SEATTLE WA | C1945: 65.98 | D1945: Dining | E1945: Luxury | F1945: usaa-cc
A1946: 45847 | B1946: Jamaican Me Crazy MARGATE CITY NJ | C1946: 67.06 | D1946: Dining | E1946: Luxury | F1946: usaa-cc
A1947: 45884 | B1947: JAMJUREE THAI SEATTLE WA | C1947: 67.68 | D1947: Dining | E1947: Luxury | F1947: usaa-cc
A1948: 45849 | B1948: AMAZON MKTPL*NL4NU0RP0 Amzn.com/billWA | C1948: 68.83 | D1948: Home & Garden | E1948: Basic | F1948: usaa-cc
A1949: 45914 | B1949: BLVD *RUDY'S LAURELHURSSEATTLE WA | C1949: 69.11 | D1949: Personal Care | E1949: Basic | F1949: usaa-cc
... A1955: 45908 | B1955: 76 - HUNGRY BEAR MARKET BELLEVUE WA | C1955: 78.41 | D1955: Groceries | E1955: Basic | F1955: usaa-cc
A1956: 45888 | B1956: SP UNIVERSITY BOOK STO 120-66343400 WA | C1956: 80.5 | D1956: 0 | E1956: 0 | F1956: usaa-cc
A1957: 45885 | B1957: TST*MEE SUM SEATTLE UNIV Seattle WA | C1957: 81.44 | D1957: Dining | E1957: Luxury | F1957: usaa-cc
A1958: 45856 | B1958: TEAMLAB PLANETS TOKYO 03-6670-3911 JP | C1958: 81.69 | D1958: Travel | E1958: Luxury | F1958: usaa-cc
A1959: 45858 | B1959: SHELL OIL 57445958606 SEATTLE WA | C1959: 82.43 | D1959: Auto | E1959: Basic | F1959: usaa-cc
A1960: 45924 | B1960: SHREE GAS STATION THORP THORP WA | C1960: 83.16 | D1960: Travel | E1960: Luxury | F1960: usaa-cc
A1961: 45918 | B1961: VAL*THE VIEW CAMPGROUN OLJATO-MONUMEAZ | C1961: 84.75 | D1961: Travel | E1961: Luxury | F1961: usaa-cc
A1962: 45919 | B1962: VAL*THE VIEW CAMPGROUN OLJATO-MONUMEAZ | C1962: 84.75 | D1962: Travel | E1962: Luxury | F1962: usaa-cc
A1963: 45858 | B1963: SQ*DENIMIO TOKYO JP | C1963: 85.64 | D1963: Travel | E1963: Luxury | F1963: usaa-cc
A1964: 45930 | B1964: PAYPAL *BLUEBIRDGRA 509-996-3526 WA | C1964: 85.66 | D1964: 0 | E1964: 0 | F1964: usaa-cc
A1965: 45886 | B1965: COSTCO GAS #1216 BELLINGHAM WA | C1965: 86.03 | D1965: Auto | E1965: Basic | F1965: usaa-cc
A1966: 45889 | B1966: SP STORY IN A BOTTLE W 142-55909326 WA | C1966: 86.5 | D1966: 0 | E1966: 0 | F1966: usaa-cc
A1967: 45821 | B1967: PAYPAL *80 20 INC 260-248-8030 IN | C1967: 86.63 | D1967: Van | E1967: Luxury | F1967: usaa-cc
A1968: 45880 | B1968: SUPER SAVE GAS #11 MERRITT CD | C1968: 86.68 | D1968: Auto | E1968: Basic | F1968: usaa-cc
A1969: 45929 | B1969: COSTCO WHSE #0001 SEATTLE WA | C1969: 86.88 | D1969: Groceries | E1969: Basic | F1969: usaa-cc
A1970: 45870 | B1970: SPOT WWW.GLOBALSTALA | C1970: 88.11 | D1970: Utilities | E1970: Basic | F1970: usaa-cc
A1971: 45848 | B1971: STONEWAY HARDWARE BALLAR SEATTLE WA | C1971: 88.27 | D1971: Home & Garden | E1971: Basic | F1971: usaa-cc
A1972: 45986 | B1972: WWW COSTCO COM | C1972: 88.27 | D1972: Groceries | E1972: Basic | F1972: usaa-cc
A1973: 45862 | B1973: THE HOME DEPOT #4702 SEATTLE WA | C1973: 88.29 | D1973: Home & Garden | E1973: Basic | F1973: usaa-cc
...

Sheet ftcu
A1: Date | B1: Payee | C1: Amount | D1: Category | E1: Bas-Lux | F1: source
A2: 45685 | B2: Ext Credit Card Credit PAYMENT - THANK YOU BEAVERTON OR | C2: -5000 | D2: =_xlfn.XLOOKUP(B2,'Payee Ref'!A:A,'Payee Ref'!B:B,"unassigned",0,1) -> Travel | E2: =_xlfn.XLOOKUP(B2,'Payee Ref'!A:A,'Payee Ref'!C:C,"unassigned",0,1) -> Luxury | F2: ftcu
A3: 45709 | B3: Ext Credit Card Credit PAYMENT - THANK YOU BEAVERTON OR | C3: -3000 | D3: =_xlfn.XLOOKUP(B3,'Payee Ref'!A:A,'Payee Ref'!B:B,"unassigned",0,1) -> Travel | E3: =_xlfn.XLOOKUP(B3,'Payee Ref'!A:A,'Payee Ref'!C:C,"unassigned",0,1) -> Luxury | F3: ftcu
A4: 45687 | B4: Ext Credit Card Credit PAYMENT - THANK YOU BEAVERTON OR | C4: -3000 | D4: =_xlfn.XLOOKUP(B4,'Payee Ref'!A:A,'Payee Ref'!B:B,"unassigned",0,1) -> Travel | E4: =_xlfn.XLOOKUP(B4,'Payee Ref'!A:A,'Payee Ref'!C:C,"unassigned",0,1) -> Luxury | F4: ftcu
A5: 45672 | B5: Ext Credit Card Credit PAYMENT - THANK YOU BEAVERTON OR | C5: -1200 | D5: =_xlfn.XLOOKUP(B5,'Payee Ref'!A:A,'Payee Ref'!B:B,"unassigned",0,1) -> Travel | E5: =_xlfn.XLOOKUP(B5,'Payee Ref'!A:A,'Payee Ref'!C:C,"unassigned",0,1) -> Luxury | F5: ftcu
A6: 45728 | B6: Ext Credit Card Credit PAYMENT - THANK YOU BEAVERTON OR | C6: -500 | D6: =_xlfn.XLOOKUP(B6,'Payee Ref'!A:A,'Payee Ref'!B:B,"unassigned",0,1) -> Travel | E6: =_xlfn.XLOOKUP(B6,'Payee Ref'!A:A,'Payee Ref'!C:C,"unassigned",0,1) -> Luxury | F6: ftcu
A7: 45909 | B7: Ext Credit Card Debit CASH ADVANCE BEAVERTON OR | C7: -316.57 | D7: =_xlfn.XLOOKUP(B7,'Payee Ref'!A:A,'Payee Ref'!B:B,"unassigned",0,1) -> Travel | E7: =_xlfn.XLOOKUP(B7,'Payee Ref'!A:A,'Payee Ref'!C:C,"unassigned",0,1) -> Luxury | F7: ftcu
A8: 45923 | B8: Ext Credit Card Credit PAYMENT - THANK YOU BEAVERTON OR | C8: -303.86 | D8: =_xlfn.XLOOKUP(B8,'Payee Ref'!A:A,'Payee Ref'!B:B,"unassigned",0,1) -> Travel | E8: =_xlfn.XLOOKUP(B8,'Payee Ref'!A:A,'Payee Ref'!C:C,"unassigned",0,1) -> Luxury | F8: ftcu
A9: 45909 | B9: Ext Credit Card Credit PAYMENT - THANK YOU BEAVERTON OR | C9: -253 | D9: =_xlfn.XLOOKUP(B9,'Payee Ref'!A:A,'Payee Ref'!B:B,"unassigned",0,1) -> Travel | E9: =_xlfn.XLOOKUP(B9,'Payee Ref'!A:A,'Payee Ref'!C:C,"unassigned",0,1) -> Luxury | F9: ftcu
A10: 45898 | B10: Ext Credit Card Debit CASH ADVANCE BEAVERTON OR | C10: -203 | D10: =_xlfn.XLOOKUP(B10,'Payee Ref'!A:A,'Payee Ref'!B:B,"unassigned",0,1) -> Travel | E10: =_xlfn.XLOOKUP(B10,'Payee Ref'!A:A,'Payee Ref'!C:C,"unassigned",0,1) -> Luxury | F10: ftcu
A11: 45929 | B11: Ext Credit Card Debit CASH ADVANCE BEAVERTON OR | C11: -104.55 | D11: =_xlfn.XLOOKUP(B11,'Payee Ref'!A:A,'Payee Ref'!B:B,"unassigned",0,1) -> Travel | E11: =_xlfn.XLOOKUP(B11,'Payee Ref'!A:A,'Payee Ref'!C:C,"unassigned",0,1) -> Luxury | F11: ftcu
A12: 45824 | B12: Ext Credit Card Debit CASH ADVANCE BEAVERTON OR | C12: -79.98 | D12: =_xlfn.XLOOKUP(B12,'Payee Ref'!A:A,'Payee Ref'!B:B,"unassigned",0,1) -> Travel | E12: =_xlfn.XLOOKUP(B12,'Payee Ref'!A:A,'Payee Ref'!C:C,"unassigned",0,1) -> Luxury | F12: ftcu
A13: 45829 | B13: Ext Credit Card Debit CASH ADVANCE BEAVERTON OR | C13: -73.19 | D13: =_xlfn.XLOOKUP(B13,'Payee Ref'!A:A,'Payee Ref'!B:B,"unassigned",0,1) -> Travel | E13: =_xlfn.XLOOKUP(B13,'Payee Ref'!A:A,'Payee Ref'!C:C,"unassigned",0,1) -> Luxury | F13: ftcu
... A110: 45715 | B110: Ext Credit Card Debit CASH ADVANCE BEAVERTON OR | C110: 22456.46 | D110: =_xlfn.XLOOKUP(B110,'Payee Ref'!A:A,'Payee Ref'!B:B,"unassigned",0,1) -> Travel | E110: =_xlfn.XLOOKUP(B110,'Payee Ref'!A:A,'Payee Ref'!C:C,"unassigned",0,1) -> Luxury | F110: ftcu
C111: =SUM(C2:C110) -> 13634.89 | E111: =SUM(E2:E110) -> 0

Sheet amex
A1: Date | B1: Payee | C1: Amount | D1: Category | E1: Bas-Lux | F1: source
A2: 45984 | B2: CURSOR, AI POWERED INEW YORK NY | C2: 22.07 | D2: =_xlfn.XLOOKUP(B2,'Payee Ref'!A:A,'Payee Ref'!B:B,"unassigned",0,1) -> Travel | E2: =_xlfn.XLOOKUP(B2,'Payee Ref'!A:A,'Payee Ref'!C:C,"unassigned",0,1) -> Luxury | F2: amex
A3: 45984 | B3: TST* TASTE OF INDIA SEATTLE WA | C3: 96.53 | D3: =_xlfn.XLOOKUP(B3,'Payee Ref'!A:A,'Payee Ref'!B:B,"unassigned",0,1) -> Dining | E3: =_xlfn.XLOOKUP(B3,'Payee Ref'!A:A,'Payee Ref'!C:C,"unassigned",0,1) -> Luxury | F3: amex
A4: 45983 | B4: ONLINE PAYMENT - THANK YOU | C4: -5520.71 | D4: =_xlfn.XLOOKUP(B4,'Payee Ref'!A:A,'Payee Ref'!B:B,"unassigned",0,1) -> Transfer | E4: =_xlfn.XLOOKUP(B4,'Payee Ref'!A:A,'Payee Ref'!C:C,"unassigned",0,1) -> Basic | F4: amex
A5: 45980 | B5: 46630 N BEND WAY 574NORTH BEND WA | C5: 61.81 | D5: =_xlfn.XLOOKUP(B5,'Payee Ref'!A:A,'Payee Ref'!B:B,"unassigned",0,1) -> Auto | E5: =_xlfn.XLOOKUP(B5,'Payee Ref'!A:A,'Payee Ref'!C:C,"unassigned",0,1) -> Basic | F5: amex
A6: 45980 | B6: DUNN LUMBER CO BELLEVUE WA | C6: 983.46 | D6: =_xlfn.XLOOKUP(B6,'Payee Ref'!A:A,'Payee Ref'!B:B,"unassigned",0,1) -> Travel | E6: =_xlfn.XLOOKUP(B6,'Payee Ref'!A:A,'Payee Ref'!C:C,"unassigned",0,1) -> Luxury | F6: amex
A7: 45980 | B7: PIE FOR THE PEOPLE NSNOQUALMIE PASS WA | C7: 9 | D7: =_xlfn.XLOOKUP(B7,'Payee Ref'!A:A,'Payee Ref'!B:B,"unassigned",0,1) -> Dining | E7: =_xlfn.XLOOKUP(B7,'Payee Ref'!A:A,'Payee Ref'!C:C,"unassigned",0,1) -> Luxury | F7: amex
A8: 45979 | B8: CLAUDE.AI SUBSCRIPTISAN FRANCISCO CA | C8: 97.74 | D8: =_xlfn.XLOOKUP(B8,'Payee Ref'!A:A,'Payee Ref'!B:B,"unassigned",0,1) -> Travel | E8: =_xlfn.XLOOKUP(B8,'Payee Ref'!A:A,'Payee Ref'!C:C,"unassigned",0,1) -> Luxury | F8: amex
A9: 45979 | B9: LEE'S SUMMIT DELI & SNOQUALMIE PS WA | C9: 2.79 | D9: =_xlfn.XLOOKUP(B9,'Payee Ref'!A:A,'Payee Ref'!B:B,"unassigned",0,1) -> Dining | E9: =_xlfn.XLOOKUP(B9,'Payee Ref'!A:A,'Payee Ref'!C:C,"unassigned",0,1) -> Luxury | F9: amex
A10: 45979 | B10: PIE FOR THE PEOPLE NSNOQUALMIE PASS WA | C10: 9 | D10: =_xlfn.XLOOKUP(B10,'Payee Ref'!A:A,'Payee Ref'!B:B,"unassigned",0,1) -> Dining | E10: =_xlfn.XLOOKUP(B10,'Payee Ref'!A:A,'Payee Ref'!C:C,"unassigned",0,1) -> Luxury | F10: amex
A11: 45978 | B11: 46630 N BEND WAY 574NORTH BEND WA | C11: 68.92 | D11: =_xlfn.XLOOKUP(B11,'Payee Ref'!A:A,'Payee Ref'!B:B,"unassigned",0,1) -> Auto | E11: =_xlfn.XLOOKUP(B11,'Payee Ref'!A:A,'Payee Ref'!C:C,"unassigned",0,1) -> Basic | F11: amex
A12: 45978 | B12: EZELLS FAMOUS CHICKESEATTLE WA | C12: 28.29 | D12: =_xlfn.XLOOKUP(B12,'Payee Ref'!A:A,'Payee Ref'!B:B,"unassigned",0,1) -> Dining | E12: =_xlfn.XLOOKUP(B12,'Payee Ref'!A:A,'Payee Ref'!C:C,"unassigned",0,1) -> Luxury | F12: amex
A13: 45978 | B13: PAYPAL *WORLDFOOTBA 9708709898 CO | C13: 34.5 | D13: =_xlfn.XLOOKUP(B13,'Payee Ref'!A:A,'Payee Ref'!B:B,"unassigned",0,1) -> Enrichment | E13: =_xlfn.XLOOKUP(B13,'Payee Ref'!A:A,'Payee Ref'!C:C,"unassigned",0,1) -> Luxury | F13: amex
... A756: 45658 | B756: SUMMIT AT SNOQUALMIESNOQUALMIE PASS WA | C756: 121.3 | D756: =_xlfn.XLOOKUP(B756,'Payee Ref'!A:A,'Payee Ref'!B:B,"unassigned",0,1) -> Enrichment | E756: =_xlfn.XLOOKUP(B756,'Payee Ref'!A:A,'Payee Ref'!C:C,"unassigned",0,1) -> Basic | F756: amex

Sheet usaa-cc
A1: Date | B1: Payee | C1: Amount | D1: Category | E1: Bas-lux | F1: source
A2: 45860 | B2: USAA CREDIT CARD PAYMENT SAN ANTONIO TX | C2: -23350.85 | D2: =_xlfn.XLOOKUP(B2,'Payee Ref'!A:A,'Payee Ref'!B:B,"unassigned",0,1) -> Credit Card Payment | E2: =_xlfn.XLOOKUP(B2,'Payee Ref'!A:A,'Payee Ref'!C:C,"unassigned",0,1) -> Basic | F2: usaa-cc
A3: 45905 | B3: USAA CREDIT CARD PAYMENT SAN ANTONIO TX | C3: -21348.38 | D3: =_xlfn.XLOOKUP(B3,'Payee Ref'!A:A,'Payee Ref'!B:B,"unassigned",0,1) -> Credit Card Payment | E3: =_xlfn.XLOOKUP(B3,'Payee Ref'!A:A,'Payee Ref'!C:C,"unassigned",0,1) -> Basic | F3: usaa-cc
A4: 45802 | B4: USAA CREDIT CARD PAYMENT SAN ANTONIO TX | C4: -20000 | D4: =_xlfn.XLOOKUP(B4,'Payee Ref'!A:A,'Payee Ref'!B:B,"unassigned",0,1) -> Credit Card Payment | E4: =_xlfn.XLOOKUP(B4,'Payee Ref'!A:A,'Payee Ref'!C:C,"unassigned",0,1) -> Basic | F4: usaa-cc
A5: 45963 | B5: USAA Credit Card | C5: -15691.03 | D5: =_xlfn.XLOOKUP(B5,'Payee Ref'!A:A,'Payee Ref'!B:B,"unassigned",0,1) -> Transfer | E5: =_xlfn.XLOOKUP(B5,'Payee Ref'!A:A,'Payee Ref'!C:C,"unassigned",0,1) -> Basic | F5: usaa-cc
A6: 45748 | B6: USAA CREDIT CARD PAYMENT SAN ANTONIO TX | C6: -15000 | D6: =_xlfn.XLOOKUP(B6,'Payee Ref'!A:A,'Payee Ref'!B:B,"unassigned",0,1) -> Credit Card Payment | E6: =_xlfn.XLOOKUP(B6,'Payee Ref'!A:A,'Payee Ref'!C:C,"unassigned",0,1) -> Basic | F6: usaa-cc
A7: 45993 | B7: USAA JJK MDS VISA PAYMENT ***********5521 | C7: -14014.11 | D7: =_xlfn.XLOOKUP(B7,'Payee Ref'!A:A,'Payee Ref'!B:B,"unassigned",0,1) -> unassigned | E7: =_xlfn.XLOOKUP(B7,'Payee Ref'!A:A,'Payee Ref'!C:C,"unassigned",0,1) -> unassigned | F7: usaa-cc
A8: 45822 | B8: USAA CREDIT CARD PAYMENT SAN ANTONIO TX | C8: -13188.92 | D8: =_xlfn.XLOOKUP(B8,'Payee Ref'!A:A,'Payee Ref'!B:B,"unassigned",0,1) -> Credit Card Payment | E8: =_xlfn.XLOOKUP(B8,'Payee Ref'!A:A,'Payee Ref'!C:C,"unassigned",0,1) -> Basic | F8: usaa-cc
A9: 45873 | B9: USAA CREDIT CARD PAYMENT SAN ANTONIO TX | C9: -10000 | D9: =_xlfn.XLOOKUP(B9,'Payee Ref'!A:A,'Payee Ref'!B:B,"unassigned",0,1) -> Credit Card Payment | E9: =_xlfn.XLOOKUP(B9,'Payee Ref'!A:A,'Payee Ref'!C:C,"unassigned",0,1) -> Basic | F9: usaa-cc
A10: 45737 | B10: USAA CREDIT CARD PAYMENT SAN ANTONIO TX | C10: -10000 | D10: =_xlfn.XLOOKUP(B10,'Payee Ref'!A:A,'Payee Ref'!B:B,"unassigned",0,1) -> Credit Card Payment | E10: =_xlfn.XLOOKUP(B10,'Payee Ref'!A:A,'Payee Ref'!C:C,"unassigned",0,1) -> Basic | F10: usaa-cc
A11: 45724 | B11: USAA CREDIT CARD PAYMENT SAN ANTONIO TX | C11: -10000 | D11: =_xlfn.XLOOKUP(B11,'Payee Ref'!A:A,'Payee Ref'!B:B,"unassigned",0,1) -> Credit Card Payment | E11: =_xlfn.XLOOKUP(B11,'Payee Ref'!A:A,'Payee Ref'!C:C,"unassigned",0,1) -> Basic | F11: usaa-cc
A12: 45696 | B12: USAA CREDIT CARD PAYMENT SAN ANTONIO TX | C12: -10000 | D12: =_xlfn.XLOOKUP(B12,'Payee Ref'!A:A,'Payee Ref'!B:B,"unassigned",0,1) -> Credit Card Payment | E12: =_xlfn.XLOOKUP(B12,'Payee Ref'!A:A,'Payee Ref'!C:C,"unassigned",0,1) -> Basic | F12: usaa-cc
A13: 45659 | B13: USAA CREDIT CARD PAYMENT SAN ANTONIO TX | C13: -10000 | D13: =_xlfn.XLOOKUP(B13,'Payee Ref'!A:A,'Payee Ref'!B:B,"unassigned",0,1) -> Credit Card Payment | E13: =_xlfn.XLOOKUP(B13,'Payee Ref'!A:A,'Payee Ref'!C:C,"unassigned",0,1) -> Basic | F13: usaa-cc
... A1930: 45977 | B1930: USAA Insurance Payment | C1930: 1233.47 | D1930: =_xlfn.XLOOKUP(B1930,'Payee Ref'!A:A,'Payee Ref'!B:B,"unassigned",0,1) -> Insurance | E1930: =_xlfn.XLOOKUP(B1930,'Payee Ref'!A:A,'Payee Ref'!C:C,"unassigned",0,1) -> Basic | F1930: usaa-cc
A1931: 46006 | B1931: USAA INSURANCE BILL PAYMENT | C1931: 1233.93 | E1931: =_xlfn.XLOOKUP(B1931,'Payee Ref'!A:A,'Payee Ref'!C:C,"unassigned",0,1) -> Basic | F1931: usaa-cc
A1932: 45823 | B1932: USAA INSURANCE PAYMENT WWW.USAA.COM TX | C1932: 1255.59 | D1932: =_xlfn.XLOOKUP(B1932,'Payee Ref'!A:A,'Payee Ref'!B:B,"unassigned",0,1) -> Insurance | E1932: =_xlfn.XLOOKUP(B1932,'Payee Ref'!A:A,'Payee Ref'!C:C,"unassigned",0,1) -> Basic | F1932: usaa-cc
A1933: 45792 | B1933: USAA INSURANCE PAYMENT WWW.USAA.COM TX | C1933: 1255.65 | D1933: =_xlfn.XLOOKUP(B1933,'Payee Ref'!A:A,'Payee Ref'!B:B,"unassigned",0,1) -> Insurance | E1933: =_xlfn.XLOOKUP(B1933,'Payee Ref'!A:A,'Payee Ref'!C:C,"unassigned",0,1) -> Basic | F1933: usaa-cc
A1934: 45762 | B1934: USAA INSURANCE PAYMENT WWW.USAA.COM TX | C1934: 1255.65 | D1934: =_xlfn.XLOOKUP(B1934,'Payee Ref'!A:A,'Payee Ref'!B:B,"unassigned",0,1) -> Insurance | E1934: =_xlfn.XLOOKUP(B1934,'Payee Ref'!A:A,'Payee Ref'!C:C,"unassigned",0,1) -> Basic | F1934: usaa-cc
A1935: 45731 | B1935: USAA INSURANCE PAYMENT WWW.USAA.COM TX | C1935: 1255.65 | D1935: =_xlfn.XLOOKUP(B1935,'Payee Ref'!A:A,'Payee Ref'!B:B,"unassigned",0,1) -> Insurance | E1935: =_xlfn.XLOOKUP(B1935,'Payee Ref'!A:A,'Payee Ref'!C:C,"unassigned",0,1) -> Basic | F1935: usaa-cc
A1936: 45703 | B1936: USAA INSURANCE PAYMENT WWW.USAA.COM TX | C1936: 1255.65 | D1936: =_xlfn.XLOOKUP(B1936,'Payee Ref'!A:A,'Payee Ref'!B:B,"unassigned",0,1) -> Insurance | E1936: =_xlfn.XLOOKUP(B1936,'Payee Ref'!A:A,'Payee Ref'!C:C,"unassigned",0,1) -> Basic | F1936: usaa-cc
A1937: 45853 | B1937: USAA INSURANCE PAYMENT WWW.USAA.COM TX | C1937: 1288.96 | D1937: =_xlfn.XLOOKUP(B1937,'Payee Ref'!A:A,'Payee Ref'!B:B,"unassigned",0,1) -> Insurance | E1937: =_xlfn.XLOOKUP(B1937,'Payee Ref'!A:A,'Payee Ref'!C:C,"unassigned",0,1) -> Basic | F1937: usaa-cc
A1938: 45697 | B1938: SQ *KATE GROSSMAN MD PLLCgosq.com WA | C1938: 1360 | D1938: =_xlfn.XLOOKUP(B1938,'Payee Ref'!A:A,'Payee Ref'!B:B,"unassigned",0,1) -> Health & Medical | E1938: =_xlfn.XLOOKUP(B1938,'Payee Ref'!A:A,'Payee Ref'!C:C,"unassigned",0,1) -> Basic | F1938: usaa-cc
A1939: 45672 | B1939: USAA INSURANCE PAYMENT WWW.USAA.COM TX | C1939: 1418.43 | D1939: =_xlfn.XLOOKUP(B1939,'Payee Ref'!A:A,'Payee Ref'!B:B,"unassigned",0,1) -> Insurance | E1939: =_xlfn.XLOOKUP(B1939,'Payee Ref'!A:A,'Payee Ref'!C:C,"unassigned",0,1) -> Basic | F1939: usaa-cc
A1940: 45739 | B1940: OPTUM CARE WA MY CHART 425-258-3900 WA | C1940: 1427.5 | D1940: =_xlfn.XLOOKUP(B1940,'Payee Ref'!A:A,'Payee Ref'!B:B,"unassigned",0,1) -> Health & Medical | E1940: =_xlfn.XLOOKUP(B1940,'Payee Ref'!A:A,'Payee Ref'!C:C,"unassigned",0,1) -> Basic | F1940: usaa-cc
A1941: 45723 | B1941: GB* SEATTLE JAZZED GIVEBUTTER.CODE | C1941: 1547.11 | D1941: =_xlfn.XLOOKUP(B1941,'Payee Ref'!A:A,'Payee Ref'!B:B,"unassigned",0,1) -> Charitable Contributions | E1941: =_xlfn.XLOOKUP(B1941,'Payee Ref'!A:A,'Payee Ref'!C:C,"unassigned",0,1) -> Basic | F1941: usaa-cc
A1942: 45795 | B1942: GLAZER'S CAMERA SEATTLE WA | C1942: 1595.61 | D1942: =_xlfn.XLOOKUP(B1942,'Payee Ref'!A:A,'Payee Ref'!B:B,"unassigned",0,1) -> Extracirricular | E1942: =_xlfn.XLOOKUP(B1942,'Payee Ref'!A:A,'Payee Ref'!C:C,"unassigned",0,1) -> Basic | F1942: usaa-cc
A1943: 45822 | B1943: SQ *KATE GROSSMAN MD PLLCgosq.com WA | C1943: 1700 | D1943: =_xlfn.XLOOKUP(B1943,'Payee Ref'!A:A,'Payee Ref'!B:B,"unassigned",0,1) -> Health & Medical | E1943: =_xlfn.XLOOKUP(B1943,'Payee Ref'!A:A,'Payee Ref'!C:C,"unassigned",0,1) -> Basic | F1943: usaa-cc
... A1954: 45862 | B1954: IN *WRIGHT DESIGNS LLC 360-5727839 WA | C1954: 9010.41 | D1954: =_xlfn.XLOOKUP(B1954,'Payee Ref'!A:A,'Payee Ref'!B:B,"unassigned",0,1) -> Van | E1954: =_xlfn.XLOOKUP(B1954,'Payee Ref'!A:A,'Payee Ref'!C:C,"unassigned",0,1) -> Luxury | F1954: usaa-cc

Sheet boa-cc
A1: Date | B1: Payee | C1: Amount | D1: Category | E1: Bas-lux | F1: source
A2: 45652 | B2: REMARKABLE OSLO | C2: -3.3 | D2: =_xlfn.XLOOKUP(B2,'Payee Ref'!A:A,'Payee Ref'!B:B,"unassigned",0,1) -> Subscriptions / Digital | E2: =_xlfn.XLOOKUP(B2,'Payee Ref'!A:A,'Payee Ref'!C:C,"unassigned",0,1) -> Luxury | F2: boa-cc
A3: 45652 | B3: SEA AIRPORT PARKING 2067874069 WA | C3: -32 | D3: =_xlfn.XLOOKUP(B3,'Payee Ref'!A:A,'Payee Ref'!B:B,"unassigned",0,1) -> Parking | E3: =_xlfn.XLOOKUP(B3,'Payee Ref'!A:A,'Payee Ref'!C:C,"unassigned",0,1) -> Basic | F3: boa-cc
A4: 45652 | B4: QFC #5807 SEATTLE WA | C4: -14.46 | D4: =_xlfn.XLOOKUP(B4,'Payee Ref'!A:A,'Payee Ref'!B:B,"unassigned",0,1) -> Groceries | E4: =_xlfn.XLOOKUP(B4,'Payee Ref'!A:A,'Payee Ref'!C:C,"unassigned",0,1) -> Basic | F4: boa-cc
A5: 45652 | B5: QFC #5807 SEATTLE WA | C5: -5.79 | D5: =_xlfn.XLOOKUP(B5,'Payee Ref'!A:A,'Payee Ref'!B:B,"unassigned",0,1) -> Groceries | E5: =_xlfn.XLOOKUP(B5,'Payee Ref'!A:A,'Payee Ref'!C:C,"unassigned",0,1) -> Basic | F5: boa-cc
A6: 45652 | B6: CRYSTAL MOUNTAIN 360-663-3020 WA | C6: -146.75 | D6: =_xlfn.XLOOKUP(B6,'Payee Ref'!A:A,'Payee Ref'!B:B,"unassigned",0,1) -> Travel | E6: =_xlfn.XLOOKUP(B6,'Payee Ref'!A:A,'Payee Ref'!C:C,"unassigned",0,1) -> Luxury | F6: boa-cc
A7: 45652 | B7: SEA SMITH COVE 6951113 888-3100583 WA | C7: -51.85 | D7: =_xlfn.XLOOKUP(B7,'Payee Ref'!A:A,'Payee Ref'!B:B,"unassigned",0,1) -> Dining | E7: =_xlfn.XLOOKUP(B7,'Payee Ref'!A:A,'Payee Ref'!C:C,"unassigned",0,1) -> Luxury | F7: boa-cc
A8: 45653 | B8: BA ELECTRONIC PAYMENT | C8: 7140.54 | D8: =_xlfn.XLOOKUP(B8,'Payee Ref'!A:A,'Payee Ref'!B:B,"unassigned",0,1) -> Credit Card Payment | E8: =_xlfn.XLOOKUP(B8,'Payee Ref'!A:A,'Payee Ref'!C:C,"unassigned",0,1) -> Basic | F8: boa-cc
A9: 45653 | B9: IN *SHADES BY MARKHAM LLC425-4430156 WA | C9: -2328.97 | D9: =_xlfn.XLOOKUP(B9,'Payee Ref'!A:A,'Payee Ref'!B:B,"unassigned",0,1) -> Home & Garden | E9: =_xlfn.XLOOKUP(B9,'Payee Ref'!A:A,'Payee Ref'!C:C,"unassigned",0,1) -> Basic | F9: boa-cc
A10: 45653 | B10: HUNGRYROOT.COM HUNGRYROOT.CONY | C10: -127.67 | D10: =_xlfn.XLOOKUP(B10,'Payee Ref'!A:A,'Payee Ref'!B:B,"unassigned",0,1) -> Groceries | E10: =_xlfn.XLOOKUP(B10,'Payee Ref'!A:A,'Payee Ref'!C:C,"unassigned",0,1) -> Basic | F10: boa-cc
A11: 45654 | B11: MAPLE LEAF ACE SEATTLE WA | C11: -78.75 | D11: =_xlfn.XLOOKUP(B11,'Payee Ref'!A:A,'Payee Ref'!B:B,"unassigned",0,1) -> Home & Garden | E11: =_xlfn.XLOOKUP(B11,'Payee Ref'!A:A,'Payee Ref'!C:C,"unassigned",0,1) -> Basic | F11: boa-cc
A12: 45656 | B12: NYTIMES* 800-698-4637 NY | C12: -25.55 | D12: =_xlfn.XLOOKUP(B12,'Payee Ref'!A:A,'Payee Ref'!B:B,"unassigned",0,1) -> Subscriptions / Digital | E12: =_xlfn.XLOOKUP(B12,'Payee Ref'!A:A,'Payee Ref'!C:C,"unassigned",0,1) -> Luxury | F12: boa-cc
A13: 45656 | B13: FULLSCRIPT* R588685504 HTTPSUS.FULLSNH | C13: -120.97 | D13: =_xlfn.XLOOKUP(B13,'Payee Ref'!A:A,'Payee Ref'!B:B,"unassigned",0,1) -> Personal Care | E13: =_xlfn.XLOOKUP(B13,'Payee Ref'!A:A,'Payee Ref'!C:C,"unassigned",0,1) -> Basic | F13: boa-cc
... A375: 45986 | B375: BA ELECTRONIC PAYMENT | C375: 7402.41 | D375: =_xlfn.XLOOKUP(B375,'Payee Ref'!A:A,'Payee Ref'!B:B,"unassigned",0,1) -> Credit Card Payment | E375: =_xlfn.XLOOKUP(B375,'Payee Ref'!A:A,'Payee Ref'!C:C,"unassigned",0,1) -> Basic | F375: boa-cc

Sheet Payee Ref
A2: Payee | B2: proper | C2: Basic/Luxury | D2: Note
A3: *LAKE CITY SEATTLE W
A4: 4490 SOUTH STATE 100MOUNT CARMEL UT | B4: Dining | C4: Luxury
A5: 46630 N BEND WAY 574NORTH BEND WA | B5: Auto | C5: Basic
A6: 46630 N BEND WAY 574NORTH BEND WA | B6: Auto | C6: Basic
A7: 6951310 - PEET'S COFSEATTLE WA | B7: Dining | C7: Luxury
A8: 7-ELEVEN 23020 SEATTLE WA | B8: Groceries | C8: Luxury | D8: should be groceries
A9: 7-ELEVEN T3 #03-12 SINGAPORE SG | B9: Travel | C9: Luxury
A10: 76 - CF UNITED APRO LLC 2BELLEVUE WA | B10: Auto | C10: Basic | D10: create category "fuel"
A11: 76 - CHELAN 76 CHELAN WA | B11: Auto | C11: Basic
A12: 76 - HUNGRY BEAR MARKET BELLEVUE WA | B12: Groceries | C12: Basic
A13: 76 - MARKET PLACE ORONDO WA | B13: Groceries | C13: Basic
A14: 76 - ROOSEVELT 76 SEATTLE WA | B14: Auto | C14: Basic
A15: 76 - THE POINT SEATTLE WA | B15: Auto | C15: Basic
A16: 76 - VILLAGE MARKET 76 SEATTLE WA | B16: Auto | C16: Basic | D16: create category "fuel"
A17: 76 Fuel | B17: Auto | C17: Basic
A18: 7E - TERMINAL 2 SINGAPORE SG | B18: Travel | C18: Luxury
A19: 8020 Inc | B19: Van | C19: Luxury
A20: A Bottle | B20: Dining | C20: Luxury
A21: A Saily | B21: Travel | C21: Luxury
A22: a.saily Lewes DE | B22: Dining | C22: Luxury
A23: AAA Membership | B23: Membership | C23: Basic
A24: AAA WA MEMBERSHIP 00 800-562-2582 WA | B24: Membership | C24: Basic
A25: AAA WA MEMBERSHIP 01 800-562-2582 WA | B25: Auto | C25: Basic
A26: ACT THEATRE WEB 206-292-7660 WA | B26: R&R | C26: Luxury | D26: shorten to R&R
A27: 81394 - WESTLAKE & TERRY SEATTLE WA
A28: ADOBE Adobe Systems SAN JOSE CA | B28: Subscriptions / Digital | C28: Luxury
A29: AER LINGUS DUBLIN CO | B29: Travel | C29: Luxury
A30: AEROP. ADOLFO SUAREZ MADRMADRID ES | B30: Travel | C30: Luxury
A31: Airbnb | B31: Travel | C31: Luxury
A32: ALADDIN GYRO RESTAURSEATTLE WA | B32: Dining | C32: Luxury
A33: Alain Bellem | B33: Home & Garden | C33: Luxury | D33: Tip for movers
A34: ALASKA AIR 0272394527601SEATTLE WA | B34: Travel | C34: Luxury | D34: shorten to travel
A35: ALASKA AIRLINES SEATTLE WA | B35: Travel | C35: Luxury
A36: ALCAMPO LOGRONO LOGRONO ES | B36: Travel | C36: Luxury
A37: ALIMENTACION PRIMOS LOGRONO ES | B37: Travel | C37: Luxury
A38: ALL THE BEST PET CARE 206-529-8000 WA | B38: Pets | C38: Luxury | D38: no change
A39: ALOFT TOKYO GINZA -C* JP | B39: Travel | C39: Luxury
A40: Amazon | B40: Home & Garden | C40: Basic
A41: AMAZON MARKEPLACE NA PA | B41: Home & Garden | C41: Basic
A42: AMAZON MARKEPLACE NA PA | B42: Home & Garden | C42: Basic
A43: AMAZON MARKEPLACE NA PA | B43: Home & Garden | C43: Basic
A44: AMAZON MARKEPLACE NA PA | B44: Home & Garden | C44: Basic
A45: AMAZON MARKEPLACE NA PA | B45: Home & Garden | C45: Basic
A46: AMAZON MKTPL*273Q84KG3 Amzn.com/billWA | B46: Home & Garden | C46: Basic | D46: change to home & garden
A47: AMAZON MKTPL*EC40N97Z3 Amzn.com/billWA | B47: Home & Garden | C47: Basic | D47: change to home & garden
A48: AMAZON MKTPL*FI8UH9NO3 Amzn.com/billWA | B48: Home & Garden | C48: Basic
A49: AMAZON MKTPL*GF1UN5B83 Amzn.com/billWA | B49: Home & Garden | C49: Basic | D49: change to home & garden
A50: AMAZON MKTPL*IF1QL9TA3 Amzn.com/billWA | B50: Home & Garden | C50: Basic
A51: AMAZON MKTPL*MW7QB7WZ3 Amzn.com/billWA | B51: Home & Garden | C51: Basic | D51: change to home & garden
A52: AMAZON MKTPL*N322C53H1 Amzn.com/billWA | B52: Home & Garden | C52: Basic
A53: AMAZON MKTPL*NI8I808V2 Amzn.com/billWA | B53: Home & Garden | C53: Basic | D53: change to home & garden
A54: AMAZON MKTPL*NL4NU0RP0 Amzn.com/billWA | B54: Home & Garden | C54: Basic
A55: AMAZON MKTPL*NN6730OD0 Amzn.com/billWA | B55: Home & Garden | C55: Basic
A56: AMAZON MKTPL*P05GB2GW3 Amzn.com/billWA | B56: Home & Garden | C56: Basic | D56: change to home & garden
A57: AMAZON MKTPL*QQ4DT5PS3 Amzn.com/billWA | B57: Home & Garden | C57: Basic | D57: change to home & garden
A58: AMAZON MKTPL*QZ40E1J43 Amzn.com/billWA | B58: Home & Garden | C58: Basic | D58: change to home & garden
A59: AMAZON MKTPL*TH6WJ55D3 Amzn.com/billWA | B59: Home & Garden | C59: Basic | D59: change to home & garden
A60: AMAZON MKTPL*US5PT8663 Amzn.com/billWA | B60: Home & Garden | C60: Basic | D60: change to home & garden
A61: AMAZON MKTPL*Z52ZS0DB1 Amzn.com/billWA | B61: Home & Garden | C61: Basic | D61: change to home & garden
A62: AMAZON MKTPL*Z54JZ8642 Amzn.com/billWA | B62: Home & Garden | C62: Basic | D62: change to home & garden
A63: AMAZON MKTPL*Z56Q89YW1 Amzn.com/billWA | B63: Home & Garden | C63: Basic | D63: change to home & garden
A64: AMAZON MKTPL*Z58Q362O1 Amzn.com/billWA | B64: Home & Garden | C64: Basic | D64: change to home & garden
A65: AMAZON MKTPL*Z702C1CJ2 Amzn.com/billWA | B65: Home & Garden | C65: Basic | D65: change to home & garden
A66: AMAZON MKTPL*Z77XG2681 Amzn.com/billWA | B66: Home & Garden | C66: Basic | D66: change to home & garden
A67: AMAZON MKTPL*Z79WK7O91 Amzn.com/billWA | B67: Home & Garden | C67: Basic | D67: change to home & garden
... A71: AMAZON MKTPL*ZG4154MU1 Amzn.com/billWA | B71: Home & Garden | C71: Basic | D71: change to home & garden
A72: AMAZON MKTPLACE PMTS | B72: Home & Garden | C72: Basic
A73: AMAZON PRIME PMTS amzn.com/billWA | B73: Home & Garden | C73: Basic | D73: change to home & garden
A74: AMAZON PRIME PMTS Amzn.com/billWA | B74: Home & Garden | C74: Basic | D74: change to home & garden
A75: AMAZON PRIME PMTS Amzn.com/bill W CREDIT | B75: Home & Garden | C75: Basic
A76: AMAZON PRIME*0T9CY5VAMZN.CO.UK/PM GB | B76: Home & Garden | C76: Basic
A77: AMAZON PRIME*213NF2FAMZN.CO.UK/PM GB | B77: Home & Garden | C77: Basic
A78: AMAZON PRIME*4624A69AMZN.CO.UK/PM GB | B78: Home & Garden | C78: Basic
A79: AMAZON PRIME*5316N72Q3 amzn.com/billWA | B79: Home & Garden | C79: Basic | D79: change to home & garden
A80: AMAZON PRIME*7R96V3LAMZN.CO.UK/PM GB | B80: Home & Garden | C80: Basic
A81: AMAZON PRIME*7X9QF4S53 Amzn.com/billWA | B81: Home & Garden | C81: Basic | D81: change to home & garden
A82: AMAZON PRIME*824L43403 amzn.com/billWA | B82: Home & Garden | C82: Basic | D82: change to home & garden
A83: AMAZON PRIME*8H20B7AAMZN.CO.UK/PM GB | B83: Home & Garden | C83: Basic
A84: AMAZON PRIME*CD8MF53T3 Amzn.com/billWA | B84: Home & Garden | C84: Basic | D84: change to home & garden
A85: AMAZON PRIME*CF97H77AMZN.CO.UK/PM GB | B85: Home & Garden | C85: Basic
A86: AMAZON PRIME*CX8JA8F93 Amzn.com/billWA | B86: Home & Garden | C86: Basic | D86: change to home & garden
A87: AMAZON PRIME*ME6UU9WAMZN.CO.UK/PM GB | B87: Home & Garden | C87: Basic
A88: AMAZON PRIME*NW4220JE2 amzn.com/billWA | B88: Home & Garden | C88: Basic | D88: change to home & garden
A89: AMAZON PRIME*NZ74Z5X60 Amzn.com/billWA | B89: Home & Garden | C89: Basic
A90: AMAZON PRIME*OR9JH8RAMZN.CO.UK/PM GB | B90: Home & Garden | C90: Basic
A91: AMAZON PRIME*P68E02BAMZN.CO.UK/PM GB | B91: Home & Garden | C91: Basic
A92: AMAZON PRIME*R20V94KAMZN.CO.UK/PM GB | B92: Home & Garden | C92: Basic
A93: AMAZON PRIME*R65X76OAMZN.CO.UK/PM GB | B93: Home & Garden | C93: Basic
A94: AMAZON PRIME*R70Z389AMZN.CO.UK/PM GB | B94: Home & Garden | C94: Basic
A95: AMAZON PRIME*RC2PT4CAMZN.CO.UK/PM GB | B95: Home & Garden | C95: Basic
A96: AMAZON PRIME*RH0065XAMZN.CO.UK/PM GB | B96: Home & Garden | C96: Basic
A97: AMAZON PRIME*RI85E93AMZN.CO.UK/PM GB | B97: Home & Garden | C97: Basic
A98: AMAZON PRIME*RM6V80PAMZN.CO.UK/PM GB | B98: Home & Garden | C98: Basic
A99: AMAZON PRIME*RT91L4HAMZN.CO.UK/PM GB | B99: Home & Garden | C99: Basic
A100: AMAZON PRIME*RV7G20WAMZN.CO.UK/PM GB | B100: Home & Garden | C100: Basic
A101: AMAZON PRIME*TK4KO2ZAMZN.CO.UK/PM GB | B101: Home & Garden | C101: Basic
A102: AMAZON PRIME*TS9O522T3 amzn.com/billWA | B102: Home & Garden | C102: Basic | D102: change to home & garden
A103: AMAZON PRIME*TV87O1CAMZN.CO.UK/PM GB | B103: Home & Garden | C103: Basic
A104: AMAZON PRIME*WD2W52KAMZN.CO.UK/PM GB | B104: Home & Garden | C104: Basic
...

Sheet Sheet7
A1: Van | B1: Luxury
A2: Van | B2: Basic
A3: Utilities | B3: Basic
A4: Unknown | B4: Basic
A5: Travel | B5: Luxury
A6: Travel | B6: Basic
A7: Transportation | B7: Basic
A8: Transfer
A9: Transfer | B9: Basic
A10: Syc | B10: Luxury
A11: Subscriptions / Digital | B11: Luxury | L11: V. FREITAS LAW, PLLC v@vfreitaslawWA
A12: Subscriptions / Digital | B12: Basic | L12: SP FELLOW PRODUCTS FELLOWPRODUCTCA
A13: R&R | B13: Luxury | L13: POKE ALICE 2 SEATTLE WA
A14: Professional | B14: Luxury | L14: TST*BA BAR - SOUTH LAKE Seattle WA
A15: Professional | B15: Basic | L15: SHORELINE SCHOOL DISTRICT206-3934215 WA
A16: Pharmacy | B16: Basic | L16: ALASKA AIR SEATTLE WA
A17: Pets | B17: Luxury | L17: ALASKA AIR 0272105262086SEATTLE WA
A18: Personal Care | B18: Basic | L18: ALASKA AIR 0272105259538SEATTLE WA
A19: Parking | B19: Basic | L19: ALASKA AIR 0272105260140SEATTLE WA
A20: Mortgage | B20: Basic | L20: ALASKA AIR 0272105260139SEATTLE WA
A21: Membership | B21: Basic | L21: NORDRACKCOM8889666283 888-966-6283 CA
A22: Membership | B22: Luxury | L22: TM *JON BATISTE 800-653-8000 CA
... A36: Gardener | B36: Luxury | L36: TST*RUBINSTEIN BAGELS - Seattle WA
A37: fue | L37: PAYPAL *IEFSPACESPT 91051816
A38: Extracirricular | B38: Basic | L38: TST*EL CAMION - SAND POI Seattle WA
A39: Enrichment | B39: Luxury | L39: SQ *JOEY UNIVERSITY VILLASeattle WA
A40: Enrichment | B40: Basic | L40: ALLIANZ TRAVEL INS ALLIANZINS.USVA
A41: Education: Secondary | B41: Basic | L41: as.Saily*saily Lewes DE
A42: Dining | B42: Luxury | L42: ALASKA AIR 0272109051092SEATTLE WA
A43: Dining | B43: Basic | L43: AIRBNB * HMKNBQB23F AIRBNB.COM CA
A44: Credit Card Payment | B44: Basic | L44: CACHITO MIO LARDERO
A45: Clothing | B45: Luxury | L45: MIKONOS GRAN VIA LOGRONO
A46: Clothing | B46: Basic | L46: SIMPLY CHILE LOGRONO
A47: Charitable Contributions | B47: Basic | L47: AIRBNB * HMSBE25BKD AIRBNB.COM CA
A48: Cash | B48: Basic | L48: WA DEPT OF HEALTH HSQA 360-236-4508 WA
A49: Boat | B49: Basic | L49: DECATHLON LOGRONO LOGRONO
... A53: Auto | B53: Luxury | L53: TST*BELLE EPICUREAN - EA Seattle WA
L54: SP SPIRITUAL GANGSTE SPIRITUALGANGCA
L55: TST*THE BRYANT CORNER CA Seattle WA
L56: PAYPAL *WORLDPACKER 786-897-1926 FL
L57: SEATTLEACADEMY 206-676-6894 WA
L58: CONVENFEE 866-492-3463 MA
L59: TST*MONSOON - BELLEVUE Bellevue WA
L60: PAYPAL *WAKAKUSA CU WAKAK402-935-7733 CA
L61: IC* INSTACART INSTACART.COMCA
L62: GOOGLE *AllTrails com 855-836-3987 CA
L63: Title Nine - Seattle Seattle WA
L64: TST*GASWORKS BREWERY Seattle WA
L65: SAFEWAY #1493 SEATAC WA
... L117: PAYPAL *BLACKSTRAP BLACKS402-935-7733 OR
